rina_pp_pyb-1.0.4.dist-info/METADATA
rina_pp_pyb-1.0.4.dist-info/WHEEL
rina_pp_pyb-1.0.4.dist-info/license_files/LICENSE
rina_pp_pyb.libs/libgcc_s-e52197c3.so.1
rina_pp_pyb/__init__.py
rina_pp_pyb/__init__.pyi
rina_pp_pyb/py.typed
rina_pp_pyb/rina_pp_pyb.cpython-310-aarch64-linux-gnu.so
rina_pp_pyb-1.0.4.dist-info/RECORD
