Metadata-Version: 2.3
Name: rina-pp-pyb
Version: 1.0.4
Classifier: Intended Audience :: Developers
Classifier: License :: OSI Approved :: MIT License
Classifier: Operating System :: OS Independent
Classifier: Programming Language :: Rust
Classifier: Programming Language :: Python :: Implementation :: CPython
Classifier: Programming Language :: Python :: Implementation :: PyPy
License-File: LICENSE
Summary: Difficulty and performance calculation for osu!
Keywords: osu,pp,stars,performance,difficulty
Author: Max Ohn <ohn.m@hotmail.de>, Simon G.
Author-email: Max Ohn <ohn.m@hotmail.de>
License: MIT
Requires-Python: >=3.7
Project-URL: Source Code, https://github.com/osuthailand/rina-pp-pyb
